scflowpy/__init__.py
scflowpy/read_sce.py
scflowpy-0.7.4.dist-info/AUTHORS.rst
scflowpy-0.7.4.dist-info/LICENSE
scflowpy-0.7.4.dist-info/METADATA
scflowpy-0.7.4.dist-info/WHEEL
scflowpy-0.7.4.dist-info/entry_points.txt
scflowpy-0.7.4.dist-info/top_level.txt
scflowpy-0.7.4.dist-info/RECORD
