Metadata-Version: 2.1
Name: scflowpy
Version: 0.7.4
Summary: Python helper functions for scFlow
Home-page: https://github.com/combiz/scflowpy
Author: Combiz Khozoie
Author-email: c.khozoie@imperial.ac.uk
License: GNU General Public License v3
Keywords: scflowpy
Classifier: Development Status :: 2 - Pre-Alpha
Classifier: Intended Audience :: Developers
Classifier: License :: OSI Approved :: GNU General Public License v3 (GPLv3)
Classifier: Natural Language :: English
Classifier: Programming Language :: Python :: 3
Classifier: Programming Language :: Python :: 3.6
Classifier: Programming Language :: Python :: 3.7
Classifier: Programming Language :: Python :: 3.8
Classifier: Programming Language :: Python :: 3.9
Requires-Python: >=3.6
License-File: LICENSE
License-File: AUTHORS.rst
Requires-Dist: anndata
Requires-Dist: rich
Requires-Dist: pip
Requires-Dist: bump2version
Requires-Dist: wheel
Requires-Dist: watchdog
Requires-Dist: flake8
Requires-Dist: tox
Requires-Dist: coverage
Requires-Dist: Sphinx
Requires-Dist: sphinx-rtd-theme
Requires-Dist: readthedocs-sphinx-search
Requires-Dist: twine
Requires-Dist: PyHamcrest
Requires-Dist: pathlib
Requires-Dist: pandas
Requires-Dist: black
Requires-Dist: isort
Requires-Dist: MarkupSafe
